[
  {
    "LapNumber": 2.0,
    "ALB": 66.23,
    "ALO": null,
    "ANT": 66.041,
    "BEA": 66.922,
    "BOR": 66.306,
    "COL": 67.516,
    "GAS": 66.8,
    "HAD": 66.577,
    "HAM": 66.297,
    "HUL": 66.653,
    "LAW": 66.651,
    "LEC": 110.169,
    "NOR": 65.412,
    "OCO": 66.959,
    "PIA": 65.794,
    "RUS": 65.914,
    "SAI": 66.086,
    "STR": null,
    "TSU": 65.928,
    "VER": 66.131
  },
  {
    "LapNumber": 3.0,
    "ALB": 129.874,
    "ALO": null,
    "ANT": null,
    "BEA": null,
    "BOR": null,
    "COL": null,
    "GAS": null,
    "HAD": 112.594,
    "HAM": 141.178,
    "HUL": null,
    "LAW": 108.589,
    "LEC": null,
    "NOR": 124.113,
    "OCO": 115.091,
    "PIA": null,
    "RUS": null,
    "SAI": null,
    "STR": null,
    "TSU": 130.799,
    "VER": 127.64
  },
  {
    "LapNumber": 4.0,
    "ALB": 105.519,
    "ALO": 66.201,
    "ANT": null,
    "BEA": null,
    "BOR": null,
    "COL": null,
    "GAS": null,
    "HAD": 95.616,
    "HAM": 116.68,
    "HUL": null,
    "LAW": 97.995,
    "LEC": null,
    "NOR": 107.205,
    "OCO": 105.499,
    "PIA": null,
    "RUS": null,
    "SAI": null,
    "STR": 66.184,
    "TSU": 132.128,
    "VER": 100.417
  },
  {
    "LapNumber": 5.0,
    "ALB": 87.057,
    "ALO": 112.484,
    "ANT": 65.526,
    "BEA": 65.861,
    "BOR": 65.6,
    "COL": 66.995,
    "GAS": 66.477,
    "HAD": 66.237,
    "HAM": 96.74,
    "HUL": 65.648,
    "LAW": 65.99,
    "LEC": 65.85,
    "NOR": 64.888,
    "OCO": 66.384,
    "PIA": 90.474,
    "RUS": 65.366,
    "SAI": 65.708,
    "STR": 119.711,
    "TSU": 65.499,
    "VER": 65.818
  },
  {
    "LapNumber": 6.0,
    "ALB": 65.839,
    "ALO": 94.759,
    "ANT": null,
    "BEA": null,
    "BOR": null,
    "COL": null,
    "GAS": null,
    "HAD": null,
    "HAM": 65.341,
    "HUL": null,
    "LAW": null,
    "LEC": null,
    "NOR": 113.16,
    "OCO": null,
    "PIA": 65.408,
    "RUS": null,
    "SAI": 116.435,
    "STR": 115.419,
    "TSU": null,
    "VER": 119.316
  },
  {
    "LapNumber": 7.0,
    "ALB": null,
    "ALO": 95.595,
    "ANT": null,
    "BEA": null,
    "BOR": null,
    "COL": null,
    "GAS": null,
    "HAD": null,
    "HAM": 127.878,
    "HUL": null,
    "LAW": null,
    "LEC": null,
    "NOR": 113.818,
    "OCO": null,
    "PIA": null,
    "RUS": null,
    "SAI": 95.904,
    "STR": 65.993,
    "TSU": null,
    "VER": 93.415
  },
  {
    "LapNumber": 8.0,
    "ALB": null,
    "ALO": 66.267,
    "ANT": 65.053,
    "BEA": 66.111,
    "BOR": 66.162,
    "COL": 98.964,
    "GAS": 65.973,
    "HAD": 66.023,
    "HAM": 65.268,
    "HUL": 66.205,
    "LAW": 65.969,
    "LEC": 65.41,
    "NOR": 64.915,
    "OCO": 66.638,
    "PIA": null,
    "RUS": 65.018,
    "SAI": 65.711,
    "STR": 129.144,
    "TSU": 66.229,
    "VER": 65.568
  },
  {
    "LapNumber": 9.0,
    "ALB": 65.461,
    "ALO": 114.241,
    "ANT": null,
    "BEA": null,
    "BOR": null,
    "COL": 66.477,
    "GAS": null,
    "HAD": 106.77,
    "HAM": null,
    "HUL": null,
    "LAW": null,
    "LEC": null,
    "NOR": null,
    "OCO": null,
    "PIA": 65.933,
    "RUS": null,
    "SAI": null,
    "STR": 107.654,
    "TSU": null,
    "VER": null
  },
  {
    "LapNumber": 10.0,
    "ALB": null,
    "ALO": 101.428,
    "ANT": null,
    "BEA": null,
    "BOR": null,
    "COL": null,
    "GAS": null,
    "HAD": 96.744,
    "HAM": null,
    "HUL": null,
    "LAW": null,
    "LEC": null,
    "NOR": null,
    "OCO": null,
    "PIA": null,
    "RUS": null,
    "SAI": null,
    "STR": 66.0,
    "TSU": null,
    "VER": null
  },
  {
    "LapNumber": 11.0,
    "ALB": null,
    "ALO": 65.925,
    "ANT": 65.467,
    "BEA": 65.366,
    "BOR": 65.182,
    "COL": null,
    "GAS": 69.61,
    "HAD": 66.053,
    "HAM": 98.974,
    "HUL": 65.505,
    "LAW": 65.182,
    "LEC": 65.157,
    "NOR": 98.956,
    "OCO": 65.557,
    "PIA": null,
    "RUS": 65.053,
    "SAI": 65.765,
    "STR": 117.2,
    "TSU": 65.139,
    "VER": 69.881
  },
  {
    "LapNumber": 12.0,
    "ALB": 65.373,
    "ALO": null,
    "ANT": null,
    "BEA": null,
    "BOR": null,
    "COL": 66.661,
    "GAS": 69.165,
    "HAD": null,
    "HAM": 78.577,
    "HUL": null,
    "LAW": null,
    "LEC": null,
    "NOR": 100.204,
    "OCO": null,
    "PIA": 86.137,
    "RUS": null,
    "SAI": null,
    "STR": 66.057,
    "TSU": null,
    "VER": 69.727
  },
  {
    "LapNumber": 13.0,
    "ALB": null,
    "ALO": null,
    "ANT": null,
    "BEA": null,
    "BOR": null,
    "COL": 114.571,
    "GAS": 69.007,
    "HAD": null,
    "HAM": 118.623,
    "HUL": null,
    "LAW": null,
    "LEC": null,
    "NOR": 90.29,
    "OCO": null,
    "PIA": 64.442,
    "RUS": null,
    "SAI": null,
    "STR": null,
    "TSU": null,
    "VER": 69.421
  },
  {
    "LapNumber": 14.0,
    "ALB": null,
    "ALO": 65.387,
    "ANT": 65.114,
    "BEA": 65.763,
    "BOR": 65.185,
    "COL": 107.511,
    "GAS": 69.142,
    "HAD": 70.987,
    "HAM": 113.003,
    "HUL": 65.283,
    "LAW": 65.249,
    "LEC": 64.574,
    "NOR": 64.324,
    "OCO": 65.519,
    "PIA": null,
    "RUS": 65.146,
    "SAI": 65.326,
    "STR": null,
    "TSU": null,
    "VER": 69.197
  },
  {
    "LapNumber": 15.0,
    "ALB": 65.314,
    "ALO": null,
    "ANT": null,
    "BEA": null,
    "BOR": null,
    "COL": 66.537,
    "GAS": 68.965,
    "HAD": null,
    "HAM": 65.384,
    "HUL": null,
    "LAW": 95.833,
    "LEC": null,
    "NOR": null,
    "OCO": null,
    "PIA": null,
    "RUS": 98.3,
    "SAI": null,
    "STR": 65.062,
    "TSU": null,
    "VER": 69.137
  },
  {
    "LapNumber": 16.0,
    "ALB": null,
    "ALO": null,
    "ANT": null,
    "BEA": null,
    "BOR": null,
    "COL": 119.318,
    "GAS": 68.987,
    "HAD": null,
    "HAM": null,
    "HUL": null,
    "LAW": 112.319,
    "LEC": null,
    "NOR": null,
    "OCO": null,
    "PIA": 64.676,
    "RUS": 126.823,
    "SAI": null,
    "STR": null,
    "TSU": 98.55,
    "VER": 69.259
  },
  {
    "LapNumber": 17.0,
    "ALB": null,
    "ALO": 65.358,
    "ANT": 114.357,
    "BEA": 65.469,
    "BOR": 101.351,
    "COL": 111.543,
    "GAS": 68.871,
    "HAD": 102.69,
    "HAM": null,
    "HUL": 109.231,
    "LAW": 67.138,
    "LEC": 74.26,
    "NOR": 99.814,
    "OCO": 66.341,
    "PIA": null,
    "RUS": 94.733,
    "SAI": 87.992,
    "STR": null,
    "TSU": null,
    "VER": 69.238
  },
  {
    "LapNumber": 18.0,
    "ALB": 65.347,
    "ALO": null,
    "ANT": null,
    "BEA": null,
    "BOR": null,
    "COL": 66.335,
    "GAS": 69.554,
    "HAD": null,
    "HAM": 64.79,
    "HUL": null,
    "LAW": 135.306,
    "LEC": 69.849,
    "NOR": null,
    "OCO": null,
    "PIA": null,
    "RUS": null,
    "SAI": 65.391,
    "STR": 66.031,
    "TSU": null,
    "VER": 69.462
  },
  {
    "LapNumber": 19.0,
    "ALB": null,
    "ALO": null,
    "ANT": null,
    "BEA": null,
    "BOR": null,
    "COL": null,
    "GAS": null,
    "HAD": null,
    "HAM": null,
    "HUL": null,
    "LAW": null,
    "LEC": 118.086,
    "NOR": null,
    "OCO": null,
    "PIA": 117.222,
    "RUS": null,
    "SAI": 114.627,
    "STR": 112.129,
    "TSU": null,
    "VER": 69.27
  },
  {
    "LapNumber": 20.0,
    "ALB": null,
    "ALO": 65.243,
    "ANT": null,
    "BEA": 127.689,
    "BOR": null,
    "COL": null,
    "GAS": null,
    "HAD": null,
    "HAM": null,
    "HUL": null,
    "LAW": null,
    "LEC": null,
    "NOR": 102.43,
    "OCO": 111.048,
    "PIA": null,
    "RUS": null,
    "SAI": 102.716,
    "STR": null,
    "TSU": null,
    "VER": null
  },
  {
    "LapNumber": 21.0,
    "ALB": 104.979,
    "ALO": null,
    "ANT": null,
    "BEA": null,
    "BOR": null,
    "COL": 65.546,
    "GAS": 65.366,
    "HAD": null,
    "HAM": 69.588,
    "HUL": null,
    "LAW": null,
    "LEC": null,
    "NOR": null,
    "OCO": null,
    "PIA": null,
    "RUS": null,
    "SAI": null,
    "STR": null,
    "TSU": null,
    "VER": null
  },
  {
    "LapNumber": 22.0,
    "ALB": null,
    "ALO": null,
    "ANT": null,
    "BEA": null,
    "BOR": null,
    "COL": null,
    "GAS": null,
    "HAD": null,
    "HAM": 101.633,
    "HUL": null,
    "LAW": null,
    "LEC": null,
    "NOR": null,
    "OCO": null,
    "PIA": null,
    "RUS": null,
    "SAI": null,
    "STR": null,
    "TSU": null,
    "VER": 64.534
  },
  {
    "LapNumber": 23.0,
    "ALB": null,
    "ALO": null,
    "ANT": null,
    "BEA": null,
    "BOR": null,
    "COL": null,
    "GAS": null,
    "HAD": null,
    "HAM": null,
    "HUL": null,
    "LAW": null,
    "LEC": null,
    "NOR": null,
    "OCO": null,
    "PIA": null,
    "RUS": null,
    "SAI": null,
    "STR": null,
    "TSU": null,
    "VER": 134.378
  },
  {
    "LapNumber": 24.0,
    "ALB": null,
    "ALO": null,
    "ANT": null,
    "BEA": null,
    "BOR": null,
    "COL": 114.898,
    "GAS": 67.674,
    "HAD": null,
    "HAM": null,
    "HUL": null,
    "LAW": null,
    "LEC": null,
    "NOR": null,
    "OCO": null,
    "PIA": null,
    "RUS": null,
    "SAI": null,
    "STR": null,
    "TSU": null,
    "VER": 118.544
  },
  {
    "LapNumber": 25.0,
    "ALB": null,
    "ALO": null,
    "ANT": null,
    "BEA": null,
    "BOR": null,
    "COL": 104.154,
    "GAS": 115.453,
    "HAD": null,
    "HAM": null,
    "HUL": null,
    "LAW": null,
    "LEC": null,
    "NOR": null,
    "OCO": null,
    "PIA": null,
    "RUS": null,
    "SAI": null,
    "STR": null,
    "TSU": null,
    "VER": 68.028
  },
  {
    "LapNumber": 26.0,
    "ALB": null,
    "ALO": null,
    "ANT": null,
    "BEA": null,
    "BOR": null,
    "COL": null,
    "GAS": null,
    "HAD": null,
    "HAM": null,
    "HUL": null,
    "LAW": null,
    "LEC": null,
    "NOR": null,
    "OCO": null,
    "PIA": null,
    "RUS": null,
    "SAI": null,
    "STR": null,
    "TSU": null,
    "VER": 133.455
  },
  {
    "LapNumber": 27.0,
    "ALB": null,
    "ALO": null,
    "ANT": null,
    "BEA": null,
    "BOR": null,
    "COL": null,
    "GAS": null,
    "HAD": null,
    "HAM": null,
    "HUL": null,
    "LAW": null,
    "LEC": null,
    "NOR": null,
    "OCO": null,
    "PIA": null,
    "RUS": null,
    "SAI": null,
    "STR": null,
    "TSU": null,
    "VER": 103.531
  }
]