[
  {
    "position": null,
    "driverCode": "VER",
    "fullName": "Max Verstappen",
    "team": "Red Bull Racing",
    "teamColor": "redbull",
    "status": "",
    "isFastestLap": false,
    "fastestLapTimeValue": null,
    "poleLapTimeValue": null,
    "points": 0.0,
    "fastestLapTime": "1:16.002",
    "lapsCompleted": 18
  },
  {
    "position": null,
    "driverCode": "NOR",
    "fullName": "Lando Norris",
    "team": "McLaren",
    "teamColor": "mclaren",
    "status": "",
    "isFastestLap": false,
    "fastestLapTimeValue": null,
    "poleLapTimeValue": null,
    "points": 0.0,
    "fastestLapTime": "1:16.597",
    "lapsCompleted": 20
  },
  {
    "position": null,
    "driverCode": "BOR",
    "fullName": "Gabriel Bortoleto",
    "team": "Kick Sauber",
    "teamColor": "alfaromeo",
    "status": "",
    "isFastestLap": false,
    "fastestLapTimeValue": null,
    "poleLapTimeValue": null,
    "points": 0.0,
    "fastestLapTime": "1:16.707",
    "lapsCompleted": 18
  },
  {
    "position": null,
    "driverCode": "HAD",
    "fullName": "Isack Hadjar",
    "team": "Racing Bulls",
    "teamColor": "alphatauri",
    "status": "",
    "isFastestLap": false,
    "fastestLapTimeValue": null,
    "poleLapTimeValue": null,
    "points": 0.0,
    "fastestLapTime": "1:16.732",
    "lapsCompleted": 18
  },
  {
    "position": null,
    "driverCode": "DOO",
    "fullName": "Jack Doohan",
    "team": "Alpine",
    "teamColor": "alpine",
    "status": "",
    "isFastestLap": false,
    "fastestLapTimeValue": null,
    "poleLapTimeValue": null,
    "points": 0.0,
    "fastestLapTime": "1:16.993",
    "lapsCompleted": 18
  },
  {
    "position": null,
    "driverCode": "GAS",
    "fullName": "Pierre Gasly",
    "team": "Alpine",
    "teamColor": "alpine",
    "status": "",
    "isFastestLap": false,
    "fastestLapTimeValue": null,
    "poleLapTimeValue": null,
    "points": 0.0,
    "fastestLapTime": "1:16.719",
    "lapsCompleted": 22
  },
  {
    "position": null,
    "driverCode": "ANT",
    "fullName": "Andrea Kimi Antonelli",
    "team": "Mercedes",
    "teamColor": "mercedes",
    "status": "",
    "isFastestLap": false,
    "fastestLapTimeValue": null,
    "poleLapTimeValue": null,
    "points": 0.0,
    "fastestLapTime": "1:16.206",
    "lapsCompleted": 20
  },
  {
    "position": null,
    "driverCode": "ALO",
    "fullName": "Fernando Alonso",
    "team": "Aston Martin",
    "teamColor": "astonmartin",
    "status": "",
    "isFastestLap": false,
    "fastestLapTimeValue": null,
    "poleLapTimeValue": null,
    "points": 0.0,
    "fastestLapTime": "1:17.270",
    "lapsCompleted": 22
  },
  {
    "position": null,
    "driverCode": "LEC",
    "fullName": "Charles Leclerc",
    "team": "Ferrari",
    "teamColor": "ferrari",
    "status": "",
    "isFastestLap": false,
    "fastestLapTimeValue": null,
    "poleLapTimeValue": null,
    "points": 0.0,
    "fastestLapTime": "1:16.188",
    "lapsCompleted": 22
  },
  {
    "position": null,
    "driverCode": "STR",
    "fullName": "Lance Stroll",
    "team": "Aston Martin",
    "teamColor": "astonmartin",
    "status": "",
    "isFastestLap": false,
    "fastestLapTimeValue": null,
    "poleLapTimeValue": null,
    "points": 0.0,
    "fastestLapTime": "1:16.948",
    "lapsCompleted": 22
  },
  {
    "position": null,
    "driverCode": "TSU",
    "fullName": "Yuki Tsunoda",
    "team": "Racing Bulls",
    "teamColor": "alphatauri",
    "status": "",
    "isFastestLap": false,
    "fastestLapTimeValue": null,
    "poleLapTimeValue": null,
    "points": 0.0,
    "fastestLapTime": "1:16.455",
    "lapsCompleted": 17
  },
  {
    "position": null,
    "driverCode": "ALB",
    "fullName": "Alexander Albon",
    "team": "Williams",
    "teamColor": "williams",
    "status": "",
    "isFastestLap": false,
    "fastestLapTimeValue": null,
    "poleLapTimeValue": null,
    "points": 0.0,
    "fastestLapTime": "1:16.258",
    "lapsCompleted": 21
  },
  {
    "position": null,
    "driverCode": "HUL",
    "fullName": "Nico Hulkenberg",
    "team": "Kick Sauber",
    "teamColor": "alfaromeo",
    "status": "",
    "isFastestLap": false,
    "fastestLapTimeValue": null,
    "poleLapTimeValue": null,
    "points": 0.0,
    "fastestLapTime": "1:17.146",
    "lapsCompleted": 15
  },
  {
    "position": null,
    "driverCode": "LAW",
    "fullName": "Liam Lawson",
    "team": "Red Bull Racing",
    "teamColor": "redbull",
    "status": "",
    "isFastestLap": false,
    "fastestLapTimeValue": null,
    "poleLapTimeValue": null,
    "points": 0.0,
    "fastestLapTime": null,
    "lapsCompleted": 2
  },
  {
    "position": null,
    "driverCode": "OCO",
    "fullName": "Esteban Ocon",
    "team": "Haas F1 Team",
    "teamColor": "haas",
    "status": "",
    "isFastestLap": false,
    "fastestLapTimeValue": null,
    "poleLapTimeValue": null,
    "points": 0.0,
    "fastestLapTime": "1:17.373",
    "lapsCompleted": 18
  },
  {
    "position": null,
    "driverCode": "HAM",
    "fullName": "Lewis Hamilton",
    "team": "Ferrari",
    "teamColor": "ferrari",
    "status": "",
    "isFastestLap": false,
    "fastestLapTimeValue": null,
    "poleLapTimeValue": null,
    "points": 0.0,
    "fastestLapTime": "1:16.378",
    "lapsCompleted": 21
  },
  {
    "position": null,
    "driverCode": "SAI",
    "fullName": "Carlos Sainz",
    "team": "Williams",
    "teamColor": "williams",
    "status": "",
    "isFastestLap": false,
    "fastestLapTimeValue": null,
    "poleLapTimeValue": null,
    "points": 0.0,
    "fastestLapTime": "1:16.252",
    "lapsCompleted": 23
  },
  {
    "position": null,
    "driverCode": "RUS",
    "fullName": "George Russell",
    "team": "Mercedes",
    "teamColor": "mercedes",
    "status": "",
    "isFastestLap": false,
    "fastestLapTimeValue": null,
    "poleLapTimeValue": null,
    "points": 0.0,
    "fastestLapTime": "1:15.960",
    "lapsCompleted": 17
  },
  {
    "position": null,
    "driverCode": "PIA",
    "fullName": "Oscar Piastri",
    "team": "McLaren",
    "teamColor": "mclaren",
    "status": "",
    "isFastestLap": false,
    "fastestLapTimeValue": null,
    "poleLapTimeValue": null,
    "points": 0.0,
    "fastestLapTime": "1:15.921",
    "lapsCompleted": 16
  },
  {
    "position": null,
    "driverCode": "BEA",
    "fullName": "Oliver Bearman",
    "team": "Haas F1 Team",
    "teamColor": "haas",
    "status": "",
    "isFastestLap": false,
    "fastestLapTimeValue": null,
    "poleLapTimeValue": null,
    "points": 0.0,
    "fastestLapTime": null,
    "lapsCompleted": 2
  }
]